spiketools/__init__.py
spiketools/version.py
spiketools/measures/__init__.py
spiketools/measures/circular.py
spiketools/measures/collections.py
spiketools/measures/conversions.py
spiketools/measures/spikes.py
spiketools/measures/trials.py
spiketools/modutils/__init__.py
spiketools/modutils/dependencies.py
spiketools/modutils/functions.py
spiketools/objects/__init__.py
spiketools/objects/session.py
spiketools/objects/unit.py
spiketools/plts/__init__.py
spiketools/plts/annotate.py
spiketools/plts/data.py
spiketools/plts/settings.py
spiketools/plts/spatial.py
spiketools/plts/spikes.py
spiketools/plts/stats.py
spiketools/plts/style.py
spiketools/plts/task.py
spiketools/plts/trials.py
spiketools/plts/utils.py
spiketools/sim/__init__.py
spiketools/sim/times.py
spiketools/sim/train.py
spiketools/sim/trials.py
spiketools/sim/utils.py
spiketools/spatial/__init__.py
spiketools/spatial/checks.py
spiketools/spatial/distance.py
spiketools/spatial/information.py
spiketools/spatial/occupancy.py
spiketools/spatial/place.py
spiketools/spatial/speed.py
spiketools/spatial/target.py
spiketools/spatial/utils.py
spiketools/stats/__init__.py
spiketools/stats/anova.py
spiketools/stats/generators.py
spiketools/stats/permutations.py
spiketools/stats/shuffle.py
spiketools/stats/trials.py
spiketools/tests/__init__.py
spiketools/tests/conftest.py
spiketools/tests/tsettings.py
spiketools/tests/tutils.py
spiketools/tests/measures/__init__.py
spiketools/tests/measures/test_circular.py
spiketools/tests/measures/test_collections.py
spiketools/tests/measures/test_conversions.py
spiketools/tests/measures/test_spikes.py
spiketools/tests/measures/test_trials.py
spiketools/tests/modutils/__init__.py
spiketools/tests/modutils/test_dependencies.py
spiketools/tests/modutils/test_functions.py
spiketools/tests/objects/__init__.py
spiketools/tests/objects/test_session.py
spiketools/tests/objects/test_unit.py
spiketools/tests/plts/__init__.py
spiketools/tests/plts/test_annotate.py
spiketools-0.2.0.dist-info/LICENSE
spiketools-0.2.0.dist-info/METADATA
spiketools-0.2.0.dist-info/WHEEL
spiketools-0.2.0.dist-info/top_level.txt
spiketools-0.2.0.dist-info/RECORD
