Metadata-Version: 2.1
Name: spiketools
Version: 0.2.0
Summary: Module for analyzing spiking data.
Home-page: https://github.com/spiketools/spiketools
Download-URL: https://github.com/spiketools/spiketools/releases
Maintainer: Thomas Donoghue
Maintainer-email: tdonoghue.research@gmail.com
License: Apache License, 2.0
Project-URL: Documentation, https://spiketools.github.io/
Project-URL: Bug Reports, https://github.com/spiketools/spike/issues
Project-URL: Source, https://github.com/spiketools/spiketools
Keywords: neuroscience,single units,spike analyses,electrophysiology
Platform: any
Classifier: Development Status :: 5 - Production/Stable
Classifier: Intended Audience :: Science/Research
Classifier: Topic :: Scientific/Engineering
Classifier: License :: OSI Approved :: Apache Software License
Classifier: Operating System :: Microsoft :: Windows
Classifier: Operating System :: MacOS
Classifier: Operating System :: POSIX
Classifier: Operating System :: Unix
Classifier: Programming Language :: Python
Classifier: Programming Language :: Python :: 3.6
Classifier: Programming Language :: Python :: 3.7
Classifier: Programming Language :: Python :: 3.8
Classifier: Programming Language :: Python :: 3.9
Classifier: Programming Language :: Python :: 3.10
Classifier: Programming Language :: Python :: 3.11
Classifier: Programming Language :: Python :: 3.12
Requires-Python: >=3.6
License-File: LICENSE
Requires-Dist: numpy
Requires-Dist: pandas
Requires-Dist: scipy
Requires-Dist: matplotlib
Provides-Extra: stats
Requires-Dist: statsmodels ; extra == 'stats'
